ctrlf_tf/__init__.py
ctrlf_tf/cli_prgm.py
ctrlf_tf/compile_utils.py
ctrlf_tf/ctrlf_core.py
ctrlf_tf/optimize_core.py
ctrlf_tf/optimize_utils.py
ctrlf_tf/parse_utils.py
ctrlf_tf/pwm_utils.py
ctrlf_tf/site_call_utils.py
ctrlf_tf/str_utils.py
ctrlf_tf/threshold_utils.py
CtrlF_TF-1.0b5.dist-info/LICENSE
CtrlF_TF-1.0b5.dist-info/METADATA
CtrlF_TF-1.0b5.dist-info/WHEEL
CtrlF_TF-1.0b5.dist-info/entry_points.txt
CtrlF_TF-1.0b5.dist-info/top_level.txt
CtrlF_TF-1.0b5.dist-info/RECORD
